kv_extractor_mcp_server/__init__.py
kv_extractor_mcp_server/__main__.py
kv_extractor_mcp_server/server.py
kv_extractor_mcp_server-0.3.2.dist-info/licenses/LICENSE
kv_extractor_mcp_server-0.3.2.dist-info/METADATA
kv_extractor_mcp_server-0.3.2.dist-info/WHEEL
kv_extractor_mcp_server-0.3.2.dist-info/entry_points.txt
kv_extractor_mcp_server-0.3.2.dist-info/top_level.txt
kv_extractor_mcp_server-0.3.2.dist-info/RECORD
