Metadata-Version: 2.4
Name: kv-extractor-mcp-server
Version: 0.3.2
Summary: Flexible Key-Value Extraction MCP Server using LLM and pydantic-ai
Author-email: KunihiroS <kunihiros@gmail.com>
License: GPL-3.0-or-later
Classifier: Programming Language :: Python :: 3.9
Classifier: Programming Language :: Python :: 3.10
Classifier: Programming Language :: Python :: 3.11
Classifier: License :: OSI Approved :: GNU General Public License v3 or later (GPLv3+)
Classifier: Operating System :: OS Independent
Classifier: Framework :: FastAPI
Requires-Python: >=3.9
License-File: LICENSE
Requires-Dist: fastmcp>=0.2.0
Requires-Dist: pydantic-ai>=0.1.4
Requires-Dist: pydantic>=2.0
Requires-Dist: PyYAML
Requires-Dist: toml
Requires-Dist: spacy>=3.7.0
Requires-Dist: langdetect
Requires-Dist: click>=8.0.0
Dynamic: license-file
